AUTHORS
LICENSE
MANIFEST.in
README.rst
setup.py
django_podcasting.egg-info/PKG-INFO
django_podcasting.egg-info/SOURCES.txt
django_podcasting.egg-info/dependency_links.txt
django_podcasting.egg-info/not-zip-safe
django_podcasting.egg-info/requires.txt
django_podcasting.egg-info/top_level.txt
podcasting/__init__.py
podcasting/admin.py
podcasting/conf.py
podcasting/feeds.py
podcasting/forms.py
podcasting/managers.py
podcasting/models.py
podcasting/urls.py
podcasting/urls_feeds.py
podcasting/views.py
podcasting/migrations/0001_initial.py
podcasting/migrations/0002_auto_20140914_2220.py
podcasting/migrations/0003_auto_20160822_2146.py
podcasting/migrations/0004_auto_20160822_2147.py
podcasting/migrations/0005_auto_20190617_1316.py
podcasting/migrations/__init__.py
podcasting/templates/podcasting/_current_episode.html
podcasting/templates/podcasting/_episode_detail.html
podcasting/templates/podcasting/_episode_list.html
podcasting/templates/podcasting/_feeds.html
podcasting/templates/podcasting/_show_detail.html
podcasting/templates/podcasting/_show_list.html
podcasting/templates/podcasting/admin_thumbnail_css.html
podcasting/templates/podcasting/admin_thumbnail_easy-thumbnails.html
podcasting/templates/podcasting/admin_thumbnail_imagekit.html
podcasting/templates/podcasting/admin_thumbnail_sorl.html
podcasting/templates/podcasting/current_episode.html
podcasting/templates/podcasting/episode_detail.html
podcasting/templates/podcasting/episode_list.html
podcasting/templates/podcasting/podcasting_base.html
podcasting/templates/podcasting/show_detail.html
podcasting/templates/podcasting/show_list.html
podcasting/tests/__init__.py
podcasting/tests/models.py
podcasting/tests/tests.py
podcasting/tests/urls.py
podcasting/utils/__init__.py
podcasting/utils/fields.py
podcasting/utils/twitter.py
podcasting/utils/widgets.py